cortex_core/__init__.py
cortex_core/_cortex_data.py
cortex_core/_drift_checks.py
cortex_core/_ethics_checks.py
cortex_core/base.py
tests/__init__.py
tests/test_cortex_data.py
tests/test_ethics_checks.py
cortex_core-1.9.2.dist-info/METADATA
cortex_core-1.9.2.dist-info/WHEEL
cortex_core-1.9.2.dist-info/top_level.txt
cortex_core-1.9.2.dist-info/RECORD
